setup.py
test/test_rw.py
ucrdtw_cffi/__init__.py
ucrdtw_cffi/cffi.py
ucrdtw_cffi/deque.c
ucrdtw_cffi/dtw.py
ucrdtw_cffi/ucr_dtw.c
utcdtw_cffi.egg-info/PKG-INFO
utcdtw_cffi.egg-info/SOURCES.txt
utcdtw_cffi.egg-info/dependency_links.txt
utcdtw_cffi.egg-info/requires.txt
utcdtw_cffi.egg-info/top_level.txt