Metadata-Version: 1.1
Name: utcdtw-cffi
Version: 0.1
Summary: CFFI binding for UTC DTW suite
Home-page: https://github.com/alendit/ucrdtw_cffi
Author: Dimitri Vorona
Author-email: vorona@in.tum.de
License: UNKNOWN
Platform: UNKNOWN
Classifier: Development Status :: 4 - Beta
Classifier: Programming Language :: Python :: 2
Classifier: Programming Language :: Python :: 3
Classifier: Programming Language :: Python :: Implementation :: PyPy
Classifier: License :: OSI Approved :: BSD License
